<SceneText>
  <Speakers>
    <Section>Speaker</Section>
  </Speakers>
  <Strings>
    <Section>Skits</Section>
    <Entry>
      <PointerOffset>2893</PointerOffset>
      <JapaneseText>医者はいないのか……？　医者はどこだ……？</JapaneseText>
      <EnglishText>Are there no doctors here?
Where could one be?</EnglishText>
      <Notes/>
      <Id>196</Id>
      <Status>Editing</Status>
    </Entry>
    <Entry>
      <PointerOffset>2921</PointerOffset>
      <JapaneseText>住民に聞いてみよう。</JapaneseText>
      <EnglishText>Let's ask the villagers.</EnglishText>
      <Notes/>
      <Id>197</Id>
      <Status>Editing</Status>
    </Entry>
  </Strings>
</SceneText>
