<SceneText>
  <Speakers>
    <Section>Speaker</Section>
  </Speakers>
  <Strings>
    <Section>Skits</Section>
    <Entry>
      <PointerOffset>2899</PointerOffset>
      <JapaneseText>終った……やっと終わったんだな……</JapaneseText>
      <EnglishText>It's over... It's finally over...</EnglishText>
      <Notes/>
      <Id>675</Id>
      <Status>Proofreading</Status>
    </Entry>
    <Entry>
      <PointerOffset>2929</PointerOffset>
      <JapaneseText>ああ、終わったんだ……
街に戻ろう……</JapaneseText>
      <EnglishText>That it is... Let's head back into town.</EnglishText>
      <Notes/>
      <Id>676</Id>
      <Status>Proofreading</Status>
    </Entry>
  </Strings>
</SceneText>
