<SceneText>
  <Speakers>
    <Section>Speaker</Section>
  </Speakers>
  <Strings>
    <Section>Skits</Section>
    <Entry>
      <PointerOffset>2868</PointerOffset>
      <JapaneseText>早く！　早くぼくに乗って！
たてがみがザワザワする！</JapaneseText>
      <EnglishText>Hurry! Hurry and get on me! I can
feel my mane standing on end!</EnglishText>
      <Notes/>
      <Id>780</Id>
      <Status>Editing</Status>
    </Entry>
    <Entry>
      <PointerOffset>2920</PointerOffset>
      <JapaneseText>すごく嫌な予感がするんだ！</JapaneseText>
      <EnglishText>Something terrible is going to happen!</EnglishText>
      <Notes/>
      <Id>781</Id>
      <Status>Editing</Status>
    </Entry>
  </Strings>
</SceneText>
