<SceneText>
  <Speakers>
    <Section>Speaker</Section>
  </Speakers>
  <Strings>
    <Section>Skits</Section>
    <Entry>
      <PointerOffset>2886</PointerOffset>
      <JapaneseText>……ジルバ・マディガン……
なぜ、ヤツを止められなかった……</JapaneseText>
      <EnglishText>Zilva Madigan... How could I have failed to stop her...?</EnglishText>
      <Notes/>
      <Id>3088</Id>
      <Status>Proofreading</Status>
    </Entry>
    <Entry>
      <PointerOffset>2913</PointerOffset>
      <JapaneseText>……こうなる前に、
打つ手はなかったのか……</JapaneseText>
      <EnglishText>Was there nothing I could have
done to prevent all of this...?</EnglishText>
      <Notes/>
      <Id>3089</Id>
      <Status>Proofreading</Status>
    </Entry>
    <Entry>
      <PointerOffset>2930</PointerOffset>
      <JapaneseText>自分を責めないで、&lt;Eugene&gt;！
悪いのはジルバなんだヨ！</JapaneseText>
      <EnglishText>Stop blaming yourself, &lt;Eugene&gt;!
Zilva was the bad guy here!</EnglishText>
      <Notes/>
      <Id>3090</Id>
      <Status>Proofreading</Status>
    </Entry>
    <Entry>
      <PointerOffset>2959</PointerOffset>
      <JapaneseText>そうさ！　あんたがいなけりゃ、
気づくヤツなんていなかった。</JapaneseText>
      <EnglishText>Yeah! If it weren't for you, no one would
have realized that something was amiss.</EnglishText>
      <Notes/>
      <Id>3091</Id>
      <Status>Proofreading</Status>
    </Entry>
    <Entry>
      <PointerOffset>2990</PointerOffset>
      <JapaneseText>すべてが終わったわけじゃない……</JapaneseText>
      <EnglishText>We're not out of the woods yet...</EnglishText>
      <Notes/>
      <Id>3092</Id>
      <Status>Proofreading</Status>
    </Entry>
    <Entry>
      <PointerOffset>3019</PointerOffset>
      <JapaneseText>ジルバに苦しめられた人たちのためにも、
オレたちにできる事をやろう……</JapaneseText>
      <EnglishText>Let's do our part for the sake of
those who suffered at Zilva's hand.</EnglishText>
      <Notes/>
      <Id>3093</Id>
      <Status>Proofreading</Status>
    </Entry>
    <Entry>
      <PointerOffset>3051</PointerOffset>
      <JapaneseText>ああ……そうだな……</JapaneseText>
      <EnglishText>Indeed, you're right.</EnglishText>
      <Notes/>
      <Id>3094</Id>
      <Status>Proofreading</Status>
    </Entry>
  </Strings>
</SceneText>
