<SceneText>
  <Strings>
    <Section>Minigame</Section>
    <Entry>
      <PointerOffset>135</PointerOffset>
      <JapaneseText>&lt;Veigue&gt;</JapaneseText>
      <EnglishText>&lt;Veigue&gt;</EnglishText>
      <Notes/>
      <Id>0</Id>
      <Status>Editing</Status>
    </Entry>
    <Entry>
      <PointerOffset>138</PointerOffset>
      <JapaneseText>stage 6</JapaneseText>
      <EnglishText>Stage 6</EnglishText>
      <Notes/>
      <Id>1</Id>
      <Status>Editing</Status>
    </Entry>
  </Strings>
</SceneText>
