<SceneText>
  <FriendlyName>Yuris' Realm - Boss Room</FriendlyName>
  <Speakers>
    <Section>Speaker</Section>
    <Entry>
      <PointerOffset/>
      <JapaneseText>[VARIABLE]</JapaneseText>
      <EnglishText>[VARIABLE]</EnglishText>
      <Notes/>
      <Id>-1</Id>
      <Status>Done</Status>
    </Entry>
    <Entry>
      <PointerOffset>4711</PointerOffset>
      <JapaneseText>&lt;Agarte&gt;</JapaneseText>
      <EnglishText>&lt;Agarte&gt;</EnglishText>
      <Notes/>
      <Id>0</Id>
      <Status>Done</Status>
    </Entry>
    <Entry>
      <PointerOffset>4685</PointerOffset>
      <JapaneseText>&lt;Claire&gt;</JapaneseText>
      <EnglishText>&lt;Claire&gt;</EnglishText>
      <Notes/>
      <Id>1</Id>
      <Status>Done</Status>
    </Entry>
    <Entry>
      <PointerOffset>4659</PointerOffset>
      <JapaneseText>ミルハウスト</JapaneseText>
      <EnglishText>Milhaust</EnglishText>
      <Notes/>
      <Id>2</Id>
      <Status>Done</Status>
    </Entry>
    <Entry>
      <PointerOffset>4548,6170</PointerOffset>
      <JapaneseText>select</JapaneseText>
      <EnglishText>Select</EnglishText>
      <Notes/>
      <Id>3</Id>
      <Status>Done</Status>
    </Entry>
  </Speakers>
  <Strings>
    <Section>system</Section>
    <Entry>
      <PointerOffset>4247</PointerOffset>
      <JapaneseText>ユリスの領域・最深部</JapaneseText>
      <EnglishText>Yuris's Realm - Deepest Layer</EnglishText>
      <Notes/>
      <Id>1</Id>
      <Status>Done</Status>
    </Entry>
    <Entry>
      <PointerOffset>4244</PointerOffset>
      <JapaneseText>ユリスの領域・最深部</JapaneseText>
      <EnglishText>Yuris's Realm - Deepest Layer</EnglishText>
      <Notes/>
      <Id>2</Id>
      <Status>Done</Status>
    </Entry>
  </Strings>
  <Strings>
    <Section>s0-0</Section>
    <Entry>
      <PointerOffset>4714</PointerOffset>
      <JapaneseText>&lt;Veigue&gt;、気をつけて……
</JapaneseText>
      <EnglishText>&lt;Veigue&gt;, please take care...</EnglishText>
      <Notes/>
      <SpeakerId>0</SpeakerId>
      <Id>3</Id>
      <Status>Proofreading</Status>
    </Entry>
  </Strings>
  <Strings>
    <Section>s0-1</Section>
    <Entry>
      <PointerOffset>4688</PointerOffset>
      <JapaneseText>みなさん、カレギアの民の心も、
あなたたちと共にあります。
</JapaneseText>
      <EnglishText>Everyone, the hearts
of Callegea's people
are with you.</EnglishText>
      <Notes/>
      <SpeakerId>1</SpeakerId>
      <Id>4</Id>
      <Status>Proofreading</Status>
    </Entry>
  </Strings>
  <Strings>
    <Section>s0-2</Section>
    <Entry>
      <PointerOffset>4662</PointerOffset>
      <JapaneseText>陛下とクレアさんは、私に任せてくれ。
</JapaneseText>
      <EnglishText>Leave Her Majesty and
Claire in my hands.</EnglishText>
      <Notes/>
      <SpeakerId>2</SpeakerId>
      <Id>5</Id>
      <Status>Proofreading</Status>
    </Entry>
  </Strings>
  <Strings>
    <Section>s1-0</Section>
    <Entry>
      <PointerOffset>4551</PointerOffset>
      <JapaneseText>進む
進まない
</JapaneseText>
      <EnglishText>Advance
Don't Advance</EnglishText>
      <Notes/>
      <SpeakerId>3</SpeakerId>
      <Id>6</Id>
      <Status>Proofreading</Status>
    </Entry>
  </Strings>
  <Strings>
    <Section>s2-0</Section>
    <Entry>
      <PointerOffset>6173</PointerOffset>
      <JapaneseText>&lt;speed:0&gt;&lt;scale:140&gt;休憩しますか？
　はい　
　いいえ　</JapaneseText>
      <EnglishText>&lt;speed:0&gt;&lt;scale:140&gt;Would you like to rest?
Yes
No</EnglishText>
      <Notes/>
      <SpeakerId>3</SpeakerId>
      <Id>7</Id>
      <Status>Done</Status>
    </Entry>
  </Strings>
</SceneText>
